opentelemetry/instrumentation/google_genai/__init__.py
opentelemetry/instrumentation/google_genai/allowlist_util.py
opentelemetry/instrumentation/google_genai/custom_semconv.py
opentelemetry/instrumentation/google_genai/dict_util.py
opentelemetry/instrumentation/google_genai/flags.py
opentelemetry/instrumentation/google_genai/generate_content.py
opentelemetry/instrumentation/google_genai/instrumentor.py
opentelemetry/instrumentation/google_genai/message.py
opentelemetry/instrumentation/google_genai/otel_wrapper.py
opentelemetry/instrumentation/google_genai/package.py
opentelemetry/instrumentation/google_genai/tool_call_wrapper.py
opentelemetry/instrumentation/google_genai/version.py
opentelemetry_instrumentation_google_genai-0.5b0.dist-info/METADATA
opentelemetry_instrumentation_google_genai-0.5b0.dist-info/WHEEL
opentelemetry_instrumentation_google_genai-0.5b0.dist-info/entry_points.txt
opentelemetry_instrumentation_google_genai-0.5b0.dist-info/licenses/LICENSE
opentelemetry_instrumentation_google_genai-0.5b0.dist-info/RECORD
