Metadata-Version: 2.4
Name: opentelemetry-instrumentation-google-genai
Version: 0.5b0
Summary: OpenTelemetry
Project-URL: Homepage, https://github.com/open-telemetry/opentelemetry-python-contrib/tree/main/instrumentation-genai/opentelemetry-instrumentation-google-genai
Project-URL: Repository, https://github.com/open-telemetry/opentelemetry-python-contrib
Author-email: OpenTelemetry Authors <cncf-opentelemetry-contributors@lists.cncf.io>
License-Expression: Apache-2.0
License-File: LICENSE
Classifier: Development Status :: 4 - Beta
Classifier: Intended Audience :: Developers
Classifier: License :: OSI Approved :: Apache Software License
Classifier: Programming Language :: Python
Classifier: Programming Language :: Python :: 3
Classifier: Programming Language :: Python :: 3.10
Classifier: Programming Language :: Python :: 3.11
Classifier: Programming Language :: Python :: 3.12
Requires-Python: >=3.9
Requires-Dist: opentelemetry-api~=1.37
Requires-Dist: opentelemetry-instrumentation<2,>=0.58b0
Requires-Dist: opentelemetry-semantic-conventions<2,>=0.58b0
Requires-Dist: opentelemetry-util-genai<0.3b0,>=0.2b0
Provides-Extra: instruments
Requires-Dist: google-genai>=1.32.0; extra == 'instruments'
